main.py
setup.py
pysisyphes.egg-info/PKG-INFO
pysisyphes.egg-info/SOURCES.txt
pysisyphes.egg-info/dependency_links.txt
pysisyphes.egg-info/requires.txt
pysisyphes.egg-info/top_level.txt